gcs_helpers/__init__.py
gcs_helpers/fetch.py
gcs_helpers/save.py
gcs_helpers/utils.py
gcs_helpers-0.0.0.24.dist-info/METADATA
gcs_helpers-0.0.0.24.dist-info/WHEEL
gcs_helpers-0.0.0.24.dist-info/entry_points.txt
gcs_helpers-0.0.0.24.dist-info/top_level.txt
gcs_helpers-0.0.0.24.dist-info/RECORD
