Metadata-Version: 2.1
Name: gcs-helpers
Version: 0.0.0.24
Summary: GCS_HELPERS: helper methods for working with google cloud storage
Home-page: https://github.com/brookisme/gcs_helpers
Author: Brookie Guzder-Williams
Author-email: brook.williams@gmail.com
License: UNKNOWN
Download-URL: https://github.com/brookisme/gcs_helpers/tarball/0.1
Keywords: python,google cloud storage,gcs
Platform: UNKNOWN
Requires-Dist: pandas
Requires-Dist: numpy
Requires-Dist: rasterio
Requires-Dist: pyyaml
Requires-Dist: affine
Requires-Dist: pyproj
Requires-Dist: geojson
